[
{"pueblo":"ALAIOR"},
{"pueblo":"ALARO"},
{"pueblo":"ALCUDIA"},
{"pueblo":"ALGAIDA"},
{"pueblo":"ALQUERIA BLANCA"},
{"pueblo":"ANDRATX"},
{"pueblo":"ARIANY"},
{"pueblo":"ARTA"},
{"pueblo":"BAIX DES PUIG"},
{"pueblo":"BAÑALBUFAR/BANYALBUFAR"},
{"pueblo":"BINIAGUAL"},
{"pueblo":"BINIALI"},
{"pueblo":"BINIAMAR"},
{"pueblo":"BINIARAIX"},
{"pueblo":"BINISSALEM"},
{"pueblo":"BUGER"},
{"pueblo":"BUNYOLA"},
{"pueblo":"CA'N PICAFORT"},
{"pueblo":"CAIMARI"},
{"pueblo":"CALA BLANCA"},
{"pueblo":"CALA BONA"},
{"pueblo":"CALA D'OR"},
{"pueblo":"CALA FIGUERA"},
{"pueblo":"CALA LLOMBARDS"},
{"pueblo":"CALA MILLOR"},
{"pueblo":"CALA MORLANDA"},
{"pueblo":"CALA MURADA"},
{"pueblo":"CALA RATJADA"},
{"pueblo":"CALA SAN VICENTE"},
{"pueblo":"CALA SANTANYI"},
{"pueblo":"CALONGE"},
{"pueblo":"CALVIA"},
{"pueblo":"CAMPANET"},
{"pueblo":"CAMPOS"},
{"pueblo":"CAPDEPERA"},
{"pueblo":"CAS CANAR"},
{"pueblo":"CAS CONCOS DES CAVALLER"},
{"pueblo":"CIUTADELLA DE MENORCA"},
{"pueblo":"COLONIA DE SANT JORDI"},
{"pueblo":"COLONIA DE SANT PERE"},
{"pueblo":"CONSELL"},
{"pueblo":"COSTITX"},
{"pueblo":"DEYA/DEIÀ"},
{"pueblo":"EL PALMER"},
{"pueblo":"EL PORT"},
{"pueblo":"ES CALO"},
{"pueblo":"ES CAPDELLA"},
{"pueblo":"ES CARREGADOR"},
{"pueblo":"ES CARRITXO"},
{"pueblo":"ES CASTELL"},
{"pueblo":"ES MERCADAL"},
{"pueblo":"ES MIGJORN GRAN"},
{"pueblo":"ES PIL.LARI"},
{"pueblo":"ES PORT DES CANONGE"},
{"pueblo":"ESCORCA"},
{"pueblo":"ESPORLES"},
{"pueblo":"ESTABLIMENTS"},
{"pueblo":"ESTELLENCS"},
{"pueblo":"FELANITX"},
{"pueblo":"FERRERIES"},
{"pueblo":"FORNALUTX"},
{"pueblo":"FORNELLS"},
{"pueblo":"GALILEA"},
{"pueblo":"IBIZA/EIVISSA"},
{"pueblo":"INCA"},
{"pueblo":"JORNETS"},
{"pueblo":"L'HORTA"},
{"pueblo":"LA GARRIGA"},
{"pueblo":"LA SAVINA"},
{"pueblo":"LLOMBARDS"},
{"pueblo":"LLORET DE VISTALEGRE"},
{"pueblo":"LLOSETA"},
{"pueblo":"LLUBI"},
{"pueblo":"LLUC"},
{"pueblo":"LLUC ALCARI"},
{"pueblo":"LLUCMAÇANES"},
{"pueblo":"LLUCMAJOR"},
{"pueblo":"MAHON/MAO"},
{"pueblo":"MANACOR"},
{"pueblo":"MANCOR DE LA VALL"},
{"pueblo":"MARIA DE LA SALUT"},
{"pueblo":"MARRATXI"},
{"pueblo":"MONTUÏRI"},
{"pueblo":"MOSCARI"},
{"pueblo":"MURO"},
{"pueblo":"NA MACARET"},
{"pueblo":"NUESTRA SEÑORA DE JESUS"},
{"pueblo":"OLLERIES"},
{"pueblo":"ORIENT"},
{"pueblo":"PALMA DE MALLORCA"},
{"pueblo":"PALMANYOLA"},
{"pueblo":"PETRA"},
{"pueblo":"PILAR DE LA MOLA"},
{"pueblo":"PINA"},
{"pueblo":"PLA DE NA TESA"},
{"pueblo":"POLLENÇA"},
{"pueblo":"PONT D'INCA"},
{"pueblo":"PORRERES"},
{"pueblo":"PORT D'ALCUDIA"},
{"pueblo":"PORT D'ANDRATX"},
{"pueblo":"PORT DE VALLDEMOSSA"},
{"pueblo":"PORTO CRISTO"},
{"pueblo":"PORTO PETRO"},
{"pueblo":"PORTOCOLOM"},
{"pueblo":"PORTOL"},
{"pueblo":"PUERTO DE POLLENÇA"},
{"pueblo":"PUIGPUNYENT"},
{"pueblo":"PUJOLS"},
{"pueblo":"RANDA"},
{"pueblo":"RUBERTS"},
{"pueblo":"S'ARANJASSA"},
{"pueblo":"S'ARENAL (Llucmajor)"},
{"pueblo":"S'ARENAL (Palma)"},
{"pueblo":"S'ARRACO"},
{"pueblo":"S'ESGLEIETA"},
{"pueblo":"S'ESTANYOL DE MIGJORN"},
{"pueblo":"S'HORTA"},
{"pueblo":"SA CABANETA"},
{"pueblo":"SA CASA BLANCA"},
{"pueblo":"SA CREU VERMELLA"},
{"pueblo":"SA POBLA"},
{"pueblo":"SA PORRASSA"},
{"pueblo":"SA RAPITA"},
{"pueblo":"SA SORDA"},
{"pueblo":"SANT ANTONI DE PORTMANY"},
{"pueblo":"SANT CLIMENT"},
{"pueblo":"SANT ELM"},
{"pueblo":"SANT FERRAN DE SES ROQUES"},
{"pueblo":"SANT FRANCESC DE FORMENTERA"},
{"pueblo":"SANT JOAN"},
{"pueblo":"SANT JOAN DE LABRITJA"},
{"pueblo":"SANT JORDI"},
{"pueblo":"SANT JORDI DE SES SALINES"},
{"pueblo":"SANT JOSEP DE SA TALAIA"},
{"pueblo":"SANT LLORENÇ DE BALAFIA"},
{"pueblo":"SANT LLORENÇ DES CARDASSAR"},
{"pueblo":"SANT LLUIS"},
{"pueblo":"SANT MATEU D'ALBARCA"},
{"pueblo":"SANT MIQUEL DE BALANSAT"},
{"pueblo":"SANT RAFEL DE SA CREU"},
{"pueblo":"SANT TOMAS"},
{"pueblo":"SANT VICENT DE SA CALA"},
{"pueblo":"SANTA AGNES DE CORONA"},
{"pueblo":"SANTA EUGENIA"},
{"pueblo":"SANTA EULALIA DEL RIO"},
{"pueblo":"SANTA GERTRUDIS"},
{"pueblo":"SANTA MARGALIDA"},
{"pueblo":"SANTA MARIA DEL CAMI"},
{"pueblo":"SANTANYI"},
{"pueblo":"SELVA"},
{"pueblo":"SENCELLES"},
{"pueblo":"SES BARDETES"},
{"pueblo":"SES COVETES"},
{"pueblo":"SES SALINES (Es Mercadal)"},
{"pueblo":"SES SALINES (Ses Salines)"},
{"pueblo":"SINEU"},
{"pueblo":"SOLLER"},
{"pueblo":"SON CARRIO"},
{"pueblo":"SON FERRIOL"},
{"pueblo":"SON MACIA"},
{"pueblo":"SON SERVERA"},
{"pueblo":"TORRET"},
{"pueblo":"TREBALUGER"},
{"pueblo":"ULLARO"},
{"pueblo":"VALLDEMOSSA"},
{"pueblo":"VILAFRANCA DE BONANY"}]