[{"pueblo":"Albufeira"},
{"pueblo":"Alcaria"},
{"pueblo":"Aldeia das Acoteias"},
{"pueblo":"Aldeia dos Matos"},
{"pueblo":"Ameijoafas"},
{"pueblo":"Areias de São João"},
{"pueblo":"Aroal"},
{"pueblo":"Azinhal"},
{"pueblo":"Barradinha"},
{"pueblo":"Branqueira"},
{"pueblo":"Brejos"},
{"pueblo":"Caliços"},
{"pueblo":"Carrasqueiro"},
{"pueblo":"Cerca Velha"},
{"pueblo":"Cerro de Águia"},
{"pueblo":"Charneca"},
{"pueblo":"Correeira"},
{"pueblo":"Ferreiras"},
{"pueblo":"Fontainhas"},
{"pueblo":"Galé"},
{"pueblo":"Galvana"},
{"pueblo":"Guia"},
{"pueblo":"Guiné"},
{"pueblo":"Lagoas"},
{"pueblo":"Matos de Cima"},
{"pueblo":"Mem Moniz"},
{"pueblo":"Monchina"},
{"pueblo":"Montechoro"},
{"pueblo":"Mosqueira"},
{"pueblo":"Olhos d'Agua"},
{"pueblo":"Olhos de Água"},
{"pueblo":"Oura"},
{"pueblo":"Paderne"},
{"pueblo":"Patã de Baixo"},
{"pueblo":"Páteo"},
{"pueblo":"Patroves"},
{"pueblo":"Poço das Canas"},
{"pueblo":"Praia da Falesia"},
{"pueblo":"Praia da Oura"},
{"pueblo":"Praia Maria Luisa"},
{"pueblo":"Purgatório"},
{"pueblo":"Ribeira de Alte"},
{"pueblo":"Roja- Pé"},
{"pueblo":"Salgados"},
{"pueblo":"Santa Eulália"},
{"pueblo":"São Rafael"},
{"pueblo":"Sesmarias"},
{"pueblo":"Terras Novas"},
{"pueblo":"Torre de Mosqueira"},
{"pueblo":"Vale da Ursa"},
{"pueblo":"Vale de Carros"},
{"pueblo":"Vale de Pedras"},
{"pueblo":"Vale de Pegas"},
{"pueblo":"Vale de Santa Maria"}]