[{"pueblo":"Água de Alte"},
{"pueblo":"Além do Rio"},
{"pueblo":"Almofala"},
{"pueblo":"Alva"},
{"pueblo":"Amial"},
{"pueblo":"Arrifana"},
{"pueblo":"Braços de Lá"},
{"pueblo":"Bustelo"},
{"pueblo":"Cabril"},
{"pueblo":"Campo Benfeito"},
{"pueblo":"Canado"},
{"pueblo":"Carvalhal"},
{"pueblo":"Carvalhas"},
{"pueblo":"Carvalhosa"},
{"pueblo":"Casais do Monte"},
{"pueblo":"Castro Daire"},
{"pueblo":"Cetos"},
{"pueblo":"Codeçais"},
{"pueblo":"Codeçal"},
{"pueblo":"Colo de Pito"},
{"pueblo":"Costilhão"},
{"pueblo":"Cotelo"},
{"pueblo":"Coura"},
{"pueblo":"Covelo de Paiva"},
{"pueblo":"Cujó"},
{"pueblo":"Eido"},
{"pueblo":"Eiriz"},
{"pueblo":"Ermida"},
{"pueblo":"Ester"},
{"pueblo":"Ester de Cima"},
{"pueblo":"Faifa"},
{"pueblo":"Farejinhas"},
{"pueblo":"Folgosa"},
{"pueblo":"Gafanhão"},
{"pueblo":"Gozende"},
{"pueblo":"Gozendinho"},
{"pueblo":"Granja"},
{"pueblo":"Grijó"},
{"pueblo":"Laboucinho"},
{"pueblo":"Lamas"},
{"pueblo":"Lamelas de Cá"},
{"pueblo":"Lamelas de Lá"},
{"pueblo":"Levadas"},
{"pueblo":"Lodeiro"},
{"pueblo":"Malhada"},
{"pueblo":"Mamouros"},
{"pueblo":"Marinheira"},
{"pueblo":"Meã"},
{"pueblo":"Mezio"},
{"pueblo":"Mões"},
{"pueblo":"Moimenta"},
{"pueblo":"Moita"},
{"pueblo":"Moledo"},
{"pueblo":"Monteiras"},
{"pueblo":"Mós"},
{"pueblo":"Mosteiro"},
{"pueblo":"Mosteiro de Cima"},
{"pueblo":"Moura Morta"},
{"pueblo":"Parada de Ester"},
{"pueblo":"Peixeninho"},
{"pueblo":"Pepim"},
{"pueblo":"Pereira"},
{"pueblo":"Pereiro"},
{"pueblo":"Picão"},
{"pueblo":"Pinheiro"},
{"pueblo":"Póvoa"},
{"pueblo":"Póvoa do Veado"},
{"pueblo":"Relva"},
{"pueblo":"Reriz"},
{"pueblo":"Ribolhinhos"},
{"pueblo":"Ribolhos"},
{"pueblo":"Rossão"},
{"pueblo":"Santa Margarida"},
{"pueblo":"Santarém"},
{"pueblo":"São Joaninho"},
{"pueblo":"Sobradinho"},
{"pueblo":"Sobrado"},
{"pueblo":"Sobreda"},
{"pueblo":"Soutelo"},
{"pueblo":"Souto"},
{"pueblo":"Tulha Nova"},
{"pueblo":"Tulha Velha"},
{"pueblo":"Vale Abrigoso"},
{"pueblo":"Vila"},
{"pueblo":"Vila Boa"},
{"pueblo":"Vila Franca"},
{"pueblo":"Vila Maior"},
{"pueblo":"Vila Meã"},
{"pueblo":"Vila Nova"},
{"pueblo":"Vila Pouca"},
{"pueblo":"Vila Seca"},
{"pueblo":"Vilar"},
{"pueblo":"Vitoreira"}]