[{"pueblo":"Adlestrop"},
{"pueblo":"Alderley"},
{"pueblo":"Alderton"},
{"pueblo":"Aldsworth"},
{"pueblo":"Alvington"},
{"pueblo":"Ampney Crucis"},
{"pueblo":"Ampney Saint Mary"},
{"pueblo":"Ampney Saint Peter"},
{"pueblo":"Andoversford"},
{"pueblo":"Arlingham"},
{"pueblo":"Arlington"},
{"pueblo":"Ashleworth"},
{"pueblo":"Ashley"},
{"pueblo":"Avening"},
{"pueblo":"Awre"},
{"pueblo":"Barnsley"},
{"pueblo":"Barnwood"},
{"pueblo":"Barton"},
{"pueblo":"Berkeley"},
{"pueblo":"Beverston"},
{"pueblo":"Bibury"},
{"pueblo":"Birdlip"},
{"pueblo":"Bishops Cleeve"},
{"pueblo":"Bisley"},
{"pueblo":"Blakeney"},
{"pueblo":"Bledington"},
{"pueblo":"Blockley"},
{"pueblo":"Bourton on the Hill"},
{"pueblo":"Bourton on the Water"},
{"pueblo":"Bream"},
{"pueblo":"Brimpsfield"},
{"pueblo":"Brimscombe"},
{"pueblo":"Broad Campden"},
{"pueblo":"Broadwell"},
{"pueblo":"Brockworth"},
{"pueblo":"Bromsberrow"},
{"pueblo":"Brookthorpe"},
{"pueblo":"Buckland"},
{"pueblo":"Bulley"},
{"pueblo":"Cam"},
{"pueblo":"Cambridge"},
{"pueblo":"Chaceley"},
{"pueblo":"Chalford"},
{"pueblo":"Charlton Abbots"},
{"pueblo":"Charlton Kings"},
{"pueblo":"Chedworth"},
{"pueblo":"Cheltenham"},
{"pueblo":"Cherington"},
{"pueblo":"Chipping Campden"},
{"pueblo":"Church End"},
{"pueblo":"Churchdown"},
{"pueblo":"Cinderford"},
{"pueblo":"Cirencester"},
{"pueblo":"Clapton"},
{"pueblo":"Claypits"},
{"pueblo":"Clearwell"},
{"pueblo":"Coaley"},
{"pueblo":"Coates"},
{"pueblo":"Coberley"},
{"pueblo":"Cold Aston"},
{"pueblo":"Coleford"},
{"pueblo":"Colesborne"},
{"pueblo":"Coln Rogers"},
{"pueblo":"Coln Saint Aldwyn"},
{"pueblo":"Coln Saint Denis"},
{"pueblo":"Condicote"},
{"pueblo":"Coombe Hill"},
{"pueblo":"Corse"},
{"pueblo":"Corse and Staunton"},
{"pueblo":"Cowley"},
{"pueblo":"Cutsdean"},
{"pueblo":"Daglingworth"},
{"pueblo":"Deerhurst"},
{"pueblo":"Didmarton"},
{"pueblo":"Donnington"},
{"pueblo":"Dowdeswell"},
{"pueblo":"Down Ampney"},
{"pueblo":"Down Hatherley"},
{"pueblo":"Drybrook"},
{"pueblo":"Dudbridge"},
{"pueblo":"Dumbleton"},
{"pueblo":"Dursley"},
{"pueblo":"Dymock"},
{"pueblo":"Eastington"},
{"pueblo":"Eastleach"},
{"pueblo":"Eastleach Martin"},
{"pueblo":"Eastleach Turville"},
{"pueblo":"Ebrington"},
{"pueblo":"Edge"},
{"pueblo":"Edgeworth"},
{"pueblo":"Elkstone"},
{"pueblo":"Elmore"},
{"pueblo":"Evenlode"},
{"pueblo":"Ewen"},
{"pueblo":"Fairford"},
{"pueblo":"Farmington"},
{"pueblo":"Flaxley"},
{"pueblo":"Framilode"},
{"pueblo":"Frampton on Severn"},
{"pueblo":"Frocester"},
{"pueblo":"Gatcombe"},
{"pueblo":"Gloucester"},
{"pueblo":"Golden Valley"},
{"pueblo":"Gotherington"},
{"pueblo":"Great Barrington"},
{"pueblo":"Great Rissington"},
{"pueblo":"Great Washbourne"},
{"pueblo":"Great Witcombe"},
{"pueblo":"Gretton"},
{"pueblo":"Guiting Power"},
{"pueblo":"Hampnett"},
{"pueblo":"Hardwicke"},
{"pueblo":"Harescombe"},
{"pueblo":"Haresfield"},
{"pueblo":"Hartpury"},
{"pueblo":"Hasfield"},
{"pueblo":"Hatherop"},
{"pueblo":"Hawling"},
{"pueblo":"Hempstead"},
{"pueblo":"Hewelsfield"},
{"pueblo":"Hillesley"},
{"pueblo":"Horsley"},
{"pueblo":"Hucclecote"},
{"pueblo":"Huntley"},
{"pueblo":"Innsworth"},
{"pueblo":"Kemble"},
{"pueblo":"Kempley"},
{"pueblo":"Kempsford"},
{"pueblo":"Kineton"},
{"pueblo":"Kingscote"},
{"pueblo":"Kingswood"},
{"pueblo":"King’s Stanley"},
{"pueblo":"Lasborough"},
{"pueblo":"Lassington"},
{"pueblo":"Lechlade"},
{"pueblo":"Leckhampton"},
{"pueblo":"Leigh"},
{"pueblo":"Leighterton"},
{"pueblo":"Little Barrington"},
{"pueblo":"Little Dean"},
{"pueblo":"Little Haresfield"},
{"pueblo":"Little Rissington"},
{"pueblo":"Little Washbourne"},
{"pueblo":"Little Witcombe"},
{"pueblo":"Long Newnton"},
{"pueblo":"Longborough"},
{"pueblo":"Longhope"},
{"pueblo":"Longney"},
{"pueblo":"Lower Cam"},
{"pueblo":"Lower Lemington"},
{"pueblo":"Lower Slaughter"},
{"pueblo":"Lower Soudley"},
{"pueblo":"Lower Swell"},
{"pueblo":"Lydbrook"},
{"pueblo":"Lydney"},
{"pueblo":"Maisemore"},
{"pueblo":"Matson"},
{"pueblo":"Meysey Hampton"},
{"pueblo":"Mickleton"},
{"pueblo":"Minchinhampton"},
{"pueblo":"Miserden"},
{"pueblo":"Mitcheldean"},
{"pueblo":"Montpellier"},
{"pueblo":"Moreton in Marsh"},
{"pueblo":"Nailsworth"},
{"pueblo":"Naunton"},
{"pueblo":"Nether Westcote"},
{"pueblo":"Newent"},
{"pueblo":"Newland"},
{"pueblo":"Newnham"},
{"pueblo":"North Cerney"},
{"pueblo":"North Nibley"},
{"pueblo":"Northleach"},
{"pueblo":"Norton"},
{"pueblo":"Notgrove"},
{"pueblo":"Nympsfield"},
{"pueblo":"Oakle Street"},
{"pueblo":"Oldbury on the Hill"},
{"pueblo":"Painswick"},
{"pueblo":"Parkend"},
{"pueblo":"Pauntley"},
{"pueblo":"Poulton"},
{"pueblo":"Preston"},
{"pueblo":"Purton"},
{"pueblo":"Quedgeley"},
{"pueblo":"Quenington"},
{"pueblo":"Randwick"},
{"pueblo":"Redmarley D’Abitot"},
{"pueblo":"Rodmarton"},
{"pueblo":"Ruardean"},
{"pueblo":"Ruardean Hill"},
{"pueblo":"Ruardean Woodside"},
{"pueblo":"Rudford"},
{"pueblo":"Ryeford"},
{"pueblo":"Saint Briavels"},
{"pueblo":"Salperton"},
{"pueblo":"Sandhurst"},
{"pueblo":"Sapperton"},
{"pueblo":"Sharpness"},
{"pueblo":"Sherbourne"},
{"pueblo":"Shipton"},
{"pueblo":"Shipton Moyne"},
{"pueblo":"Shurdington"},
{"pueblo":"Siddington"},
{"pueblo":"Slimbridge"},
{"pueblo":"Snowshill"},
{"pueblo":"Somerford Keynes"},
{"pueblo":"South Cerney"},
{"pueblo":"Southam"},
{"pueblo":"Southrop"},
{"pueblo":"Standish"},
{"pueblo":"Stanton"},
{"pueblo":"Stanway"},
{"pueblo":"Staunton"},
{"pueblo":"Staverton"},
{"pueblo":"Stone"},
{"pueblo":"Stonehouse"},
{"pueblo":"Stow on the Wold"},
{"pueblo":"Stroud"},
{"pueblo":"Swindon"},
{"pueblo":"Syde"},
{"pueblo":"Tarlton"},
{"pueblo":"Teddington"},
{"pueblo":"Temple Guiting"},
{"pueblo":"Tetbury"},
{"pueblo":"Tewkesbury"},
{"pueblo":"Tibberton"},
{"pueblo":"Tidenham"},
{"pueblo":"Tirley"},
{"pueblo":"Toddington"},
{"pueblo":"Todenham"},
{"pueblo":"Tredington"},
{"pueblo":"Turkdean"},
{"pueblo":"Tutshill"},
{"pueblo":"Uley"},
{"pueblo":"Upleadon"},
{"pueblo":"Upper Slaughter"},
{"pueblo":"Upper Swell"},
{"pueblo":"Upton St Leonards"},
{"pueblo":"Westbury on Severn"},
{"pueblo":"Westfield"},
{"pueblo":"Weston Subedge"},
{"pueblo":"Whelford"},
{"pueblo":"Whitecroft"},
{"pueblo":"Whittington"},
{"pueblo":"Winchcombe"},
{"pueblo":"Windrush"},
{"pueblo":"Winson"},
{"pueblo":"Withington"},
{"pueblo":"Woodchester"},
{"pueblo":"Woodmancote"},
{"pueblo":"Woolaston"},
{"pueblo":"Woolstone"},
{"pueblo":"Wormington"},
{"pueblo":"Wotton-under-Edge"},
{"pueblo":"Wyck Rissington"},
{"pueblo":"Yanworth"}]